wireless_control.py
wireless_control-0.1.1.dist-info/METADATA
wireless_control-0.1.1.dist-info/RECORD
wireless_control-0.1.1.dist-info/WHEEL
wireless_control-0.1.1.dist-info/top_level.txt
