Metadata-Version: 2.1
Name: wireless-control
Version: 0.1.1
Summary: A command line wireless control tool for Android.
Home-page: https://github.com/fjwCode/wireless-control
Author: White Turing
Author-email: fujiawei@stu.hznu.edu.cn
License: BSD
Keywords: android,control,automation,testing,cerium
Platform: Windows
Classifier: Intended Audience :: Developers
Classifier: License :: OSI Approved :: BSD License
Classifier: Operating System :: Microsoft :: Windows
Classifier: Programming Language :: Python :: 3.6
Classifier: Programming Language :: Python :: Implementation :: CPython
Classifier: Programming Language :: Python :: Implementation :: PyPy
Classifier: Topic :: Software Development :: Testing
Classifier: Topic :: Software Development :: Libraries :: Python Modules
Requires-Python: >=3.6.0
Requires-Dist: cerium (>=1.2.0)
Requires-Dist: prompt-toolkit (>=1.0.15)
